lab04_fsm/src/test_program.sv
module test_program(
    input logic clk,
    output logic rst_n,
    output logic start_fsm,
    input logic [1:0] cs_fsm
);

    initial begin
        $display("%0d", $time, " ns, start");
        rst_n = 0;
        start_fsm = 0; 
        #100;
        rst_n = 1;
        #100;
        start_fsm = 1;
        wait(cs_fsm == 2'd3);
        $display("%0d", $time, " ns, cs = LAST");
        start_fsm = 0;
        #100; 
        $display("%0d", $time, " ns, finish");
        $finish;
    end
endmodule

lab04_fsm/src/design_fsm.sv
module design_fsm( 
    input logic  clk,   //port
    input logic  rst_n, //port
    input logic  start_fsm,
    output logic [1:0] cs_fsm
);
    //In fsm, localparam cannot be overrided in inst
	//parameter IDLE = 0; <-- this is also possible
    localparam IDLE   = 0;
    localparam FIRST  = 1;
    localparam SECOND = 2;
    localparam LAST   = 3;

    logic [1:0] cs; //current state, unknown 
    logic [1:0] ns; //next state
	
    assign cs_fsm = cs;
	
	//seq logic
    always @(posedge clk) begin
        if(!rst_n) begin
            cs <= IDLE; 
        end else begin
            cs <= ns;
        end
    end
	
	//comb logic
    always @(*) begin
        case(cs) 
            IDLE: 
                ns = (start_fsm) ? FIRST: IDLE;  // (condition)? cond==1: cond==0
            FIRST:
                ns = SECOND;
				//ns = FIRST, <---bug
            SECOND:
                ns= LAST;
            LAST:
                ns = IDLE;
            default:
                ns = IDLE;
        endcase   
    end
	
/*
	logic [254:0] abc; 
    always @(posedge clk) begin
        if(!rst_n) begin
            abc <= 0;  
        end else begin (start_fsm)
            abc <= abc + 1;
        end
    end
*/
endmodule

lab04_fsm/src/clkgen.sv
module clkgen #(parameter HALF_PERIOD=50) (output logic clk); //clock generator
    initial  clk=0;
    always begin
        #HALF_PERIOD clk = ~clk;
    end
endmodule

lab04_fsm/src/top.sv
module top;
    logic clk;
    logic rst_n;     //reset flip-flop
    logic start_fsm; //to trigger fsm
    logic [1:0] cs_fsm;    //current state of fsm, driver -> gate -> load

    clkgen #(.HALF_PERIOD(5)) inst_clkgen(   //instance
        .clk(clk)
    );
	
    // design
    design_fsm inst_design_fsm (
        .*
    );
    /* 
	//the following is the complete port connnection
	
	design_fsm inst_design_fsm (
        .port_name(signal_name),
    );
	
	design_fsm inst_design_fsm (
        .clk(clk),
		.rst_n(rst_n),
		.start_fsm(start_fsm),
		.cs_fsm(cs_fsm)
    );
	*/
	
    // test program
    test_program inst_test_program (
        .*
    );
	
	logic [3:0] total = 4'b0011; //total[3], total[2], total[1], total[0]
	logic bit_sel = total[1]; //1
	logic [1:0] part_sel = total[2:1]; //01
	logic [1:0] part_sel2 = total[5:4]; //xx, error case
	
	initial begin
		$dumpfile("top.vcd");
		$dumpvars;
    end
endmodule

lab04_fsm/top.vcd
$date
	Thu Feb 29 21:12:41 2024
$end
$version
	Icarus Verilog
$end
$timescale
	1s
$end
$scope module top $end
$var wire 1 ! start_fsm $end
$var wire 1 " rst_n $end
$var wire 2 # cs_fsm [1:0] $end
$var wire 1 $ clk $end
$var reg 1 % bit_sel $end
$var reg 2 & part_sel [1:0] $end
$var reg 4 ' total [3:0] $end
$scope module inst_clkgen $end
$var parameter 32 ( HALF_PERIOD $end
$var reg 1 $ clk $end
$upscope $end
$scope module inst_design_fsm $end
$var wire 1 $ clk $end
$var wire 2 ) cs_fsm [1:0] $end
$var wire 1 ! start_fsm $end
$var wire 1 " rst_n $end
$var parameter 32 * FIRST $end
$var parameter 32 + IDLE $end
$var parameter 32 , LAST $end
$var parameter 32 - SECOND $end
$var reg 2 . cs [1:0] $end
$var reg 2 / ns [1:0] $end
$upscope $end
$scope module inst_test_program $end
$var wire 1 $ clk $end
$var wire 2 0 cs_fsm [1:0] $end
$var reg 1 " rst_n $end
$var reg 1 ! start_fsm $end
$upscope $end
$upscope $end
$enddefinitions $end
$comment Show the parameter values. $end
$dumpall
b10 -
b11 ,
b0 +
b1 *
b101 (
$end
#0
$dumpvars
bx 0
b0 /
bx .
bx )
b11 '
bx &
1%
0$
bx #
0"
0!
$end
#5
b0 #
b0 )
b0 0
b0 .
1$
#10
0$
#15
1$
#20
0$
#25
1$
#30
0$
#35
1$
#40
0$
#45
1$
#50
0$
#55
1$
#60
0$
#65
1$
#70
0$
#75
1$
#80
0$
#85
1$
#90
0$
#95
1$
#100
0$
1"
#105
1$
#110
0$
#115
1$
#120
0$
#125
1$
#130
0$
#135
1$
#140
0$
#145
1$
#150
0$
#155
1$
#160
0$
#165
1$
#170
0$
#175
1$
#180
0$
#185
1$
#190
0$
#195
1$
#200
b1 /
0$
1!
#205
b10 /
b1 #
b1 )
b1 0
b1 .
1$
#210
0$
#215
b11 /
b10 #
b10 )
b10 0
b10 .
1$
#220
0$
#225
b0 /
0!
b11 #
b11 )
b11 0
b11 .
1$
#230
0$
#235
b0 #
b0 )
b0 0
b0 .
1$
