lab04_fsm/src/test_program.sv
module test_program(
    input logic clk,
    output logic rst_n,
    output logic start_fsm,
    input logic [1:0] cs_fsm
);

    initial begin
        $display("%0d", $time, " ns, start");
        rst_n = 0;
        start_fsm = 0; 
        #100;
        rst_n = 1;
        #100;
        start_fsm = 1;
        wait(cs_fsm == 2'd3);
        $display("%0d", $time, " ns, cs = LAST");
        start_fsm = 0;
        #100; 
        $display("%0d", $time, " ns, finish");
        $finish;
    end
endmodule

lab04_fsm/src/design_fsm.sv
module design_fsm(
    input logic  clk,
    input logic  rst_n,   
    input logic  start_fsm,
    output logic [1:0] cs_fsm
);
    //localparam cannot be overrided in inst
    localparam IDLE   = 0;
    localparam FIRST  = 1;
    localparam SECOND = 2;
    localparam LAST   = 3;

    logic [1:0] cs; //current state
    logic [1:0] ns; //next state

    assign cs_fsm = cs;

    always @(posedge clk) begin
        if(!rst_n) begin
            cs <= IDLE;
        end else begin
            cs <= ns;
        end
    end

    always @(*) begin
        case(cs) 
            IDLE: 
                ns = (start_fsm) ? FIRST: IDLE;
            FIRST:
                ns = SECOND;
            SECOND:
                ns= LAST;
            LAST:
                ns = IDLE;
            default:
                ns = IDLE;
        endcase   
    end

endmodule

lab04_fsm/src/clkgen.sv
module clkgen #(parameter HALF_PERIOD=50) (output logic clk);
    initial  clk=0;
    always begin
        #HALF_PERIOD clk = ~clk;
    end
endmodule

lab04_fsm/src/top.sv
module top;
    logic clk;
    logic rst_n;     //reset flip-flop
    logic start_fsm; //to trigger fsm
    logic [1:0] cs_fsm;    //current state of fsm

    logic bit_sel  = cs_fsm[1];   //index
    logic part_sel = cs_fsm[1:0]; //slice

    clkgen #(.HALF_PERIOD(5)) inst_clkgen(
        .clk(clk)
    );

    // design
    design_fsm inst_design_fsm (
        .*
    );

    // test program
    test_program inst_test_program (
        .*
    );
	
	initial begin
		$dumpfile("top.vcd");
		$dumpvars;
    end
endmodule

lab04_fsm/top.vcd
$date
	Fri Jan 12 14:09:45 2024
$end
$version
	Icarus Verilog
$end
$timescale
	1ps
$end
$scope module top $end
$var wire 1 ! start_fsm $end
$var wire 1 " rst_n $end
$var wire 2 # cs_fsm [1:0] $end
$var wire 1 $ clk $end
$var reg 1 % bit_sel $end
$var reg 1 & part_sel $end
$scope module inst_clkgen $end
$var parameter 32 ' HALF_PERIOD $end
$var reg 1 $ clk $end
$upscope $end
$scope module inst_design_fsm $end
$var wire 1 $ clk $end
$var wire 2 ( cs_fsm [1:0] $end
$var wire 1 ! start_fsm $end
$var wire 1 " rst_n $end
$var parameter 32 ) FIRST $end
$var parameter 32 * IDLE $end
$var parameter 32 + LAST $end
$var parameter 32 , SECOND $end
$var reg 2 - cs [1:0] $end
$var reg 2 . ns [1:0] $end
$upscope $end
$scope module inst_test_program $end
$var wire 1 $ clk $end
$var wire 2 / cs_fsm [1:0] $end
$var reg 1 " rst_n $end
$var reg 1 ! start_fsm $end
$upscope $end
$upscope $end
$enddefinitions $end
$comment Show the parameter values. $end
$dumpall
b10 ,
b11 +
b0 *
b1 )
b101 '
$end
#0
$dumpvars
bx /
b0 .
bx -
bx (
x&
x%
0$
bx #
0"
0!
$end
#5000000000000
b0 #
b0 (
b0 /
b0 -
1$
#10000000000000
0$
#15000000000000
1$
#20000000000000
0$
#25000000000000
1$
#30000000000000
0$
#35000000000000
1$
#40000000000000
0$
#45000000000000
1$
#50000000000000
0$
#55000000000000
1$
#60000000000000
0$
#65000000000000
1$
#70000000000000
0$
#75000000000000
1$
#80000000000000
0$
#85000000000000
1$
#90000000000000
0$
#95000000000000
1$
#100000000000000
0$
1"
#105000000000000
1$
#110000000000000
0$
#115000000000000
1$
#120000000000000
0$
#125000000000000
1$
#130000000000000
0$
#135000000000000
1$
#140000000000000
0$
#145000000000000
1$
#150000000000000
0$
#155000000000000
1$
#160000000000000
0$
#165000000000000
1$
#170000000000000
0$
#175000000000000
1$
#180000000000000
0$
#185000000000000
1$
#190000000000000
0$
#195000000000000
1$
#200000000000000
b1 .
0$
1!
#205000000000000
b10 .
b1 #
b1 (
b1 /
b1 -
1$
#210000000000000
0$
#215000000000000
b11 .
b10 #
b10 (
b10 /
b10 -
1$
#220000000000000
0$
#225000000000000
b0 .
0!
b11 #
b11 (
b11 /
b11 -
1$
#230000000000000
0$
#235000000000000
b0 #
b0 (
b0 /
b0 -
1$
