lab03_counter/src/top.sv
/*
	lab03
*/
module top;
	bit clk;    //clock
	logic [1:0] cnt_2bits = 2'd0;  //counter packed
	logic [2:0] cnt_3bits  = 3'd0; //packed. cannot be unpacked
	int cnt_int = 0; //32-bits
	byte my_byte; //8-bits, concat by sig1 and sig2
	
	bit [1:0] sig1 = 2'b10;
	bit [5:0] sig2 = 6'b111111;
	
	//assign my_byte = {sig1, sig2};  conti-assignment
	
	always #5 clk = ~clk; //clock with period 10sec

	always @(edge clk) begin
		cnt_2bits <= cnt_2bits + 1;
    end
	
	always @(posedge clk) begin
		cnt_3bits <= cnt_3bits + 1;
    end
	
	always @(posedge clk) begin
		cnt_int <= cnt_int + 1;
    end
	
    initial begin
        $dumpfile("top.vcd");
		$dumpvars;
		my_byte = {sig1, sig2}; //MSB LSB
		#10;
		my_byte = {sig2, sig1}; //MSB LSB
		#1000; 
		$display("at time = ", $time, " end of the sim");
		$finish;    
    end
endmodule

lab03_counter/top.vcd
$date
	Thu Feb 01 22:06:51 2024
$end
$version
	Icarus Verilog
$end
$timescale
	1s
$end
$scope module top $end
$var reg 2 ! cnt_2bits [1:0] $end
$var reg 3 " cnt_3bits [2:0] $end
$var reg 1 # clk $end
$var integer 32 $ cnt_int [31:0] $end
$var reg 8 % my_byte [7:0] $end
$var reg 2 & sig1 [1:0] $end
$var reg 6 ' sig2 [5:0] $end
$upscope $end
$enddefinitions $end
$comment Show the parameter values. $end
$dumpall
$end
#0
$dumpvars
b111111 '
b10 &
b10111111 %
b0 $
0#
b0 "
b0 !
$end
#5
b1 "
b1 $
b1 !
1#
#10
b10 !
0#
b11111110 %
#15
b10 $
b10 "
b11 !
1#
#20
b0 !
0#
#25
b11 "
b11 $
b1 !
1#
#30
b10 !
0#
#35
b100 $
b100 "
b11 !
1#
#40
b0 !
0#
#45
b101 "
b101 $
b1 !
1#
#50
b10 !
0#
#55
b110 $
b110 "
b11 !
1#
#60
b0 !
0#
#65
b111 "
b111 $
b1 !
1#
#70
b10 !
0#
#75
b1000 $
b0 "
b11 !
1#
#80
b0 !
0#
#85
b1 "
b1001 $
b1 !
1#
#90
b10 !
0#
#95
b1010 $
b10 "
b11 !
1#
#100
b0 !
0#
#105
b11 "
b1011 $
b1 !
1#
#110
b10 !
0#
#115
b1100 $
b100 "
b11 !
1#
#120
b0 !
0#
#125
b101 "
b1101 $
b1 !
1#
#130
b10 !
0#
#135
b1110 $
b110 "
b11 !
1#
#140
b0 !
0#
#145
b111 "
b1111 $
b1 !
1#
#150
b10 !
0#
#155
b10000 $
b0 "
b11 !
1#
#160
b0 !
0#
#165
b1 "
b10001 $
b1 !
1#
#170
b10 !
0#
#175
b10010 $
b10 "
b11 !
1#
#180
b0 !
0#
#185
b11 "
b10011 $
b1 !
1#
#190
b10 !
0#
#195
b10100 $
b100 "
b11 !
1#
#200
b0 !
0#
#205
b101 "
b10101 $
b1 !
1#
#210
b10 !
0#
#215
b10110 $
b110 "
b11 !
1#
#220
b0 !
0#
#225
b111 "
b10111 $
b1 !
1#
#230
b10 !
0#
#235
b11000 $
b0 "
b11 !
1#
#240
b0 !
0#
#245
b1 "
b11001 $
b1 !
1#
#250
b10 !
0#
#255
b11010 $
b10 "
b11 !
1#
#260
b0 !
0#
#265
b11 "
b11011 $
b1 !
1#
#270
b10 !
0#
#275
b11100 $
b100 "
b11 !
1#
#280
b0 !
0#
#285
b101 "
b11101 $
b1 !
1#
#290
b10 !
0#
#295
b11110 $
b110 "
b11 !
1#
#300
b0 !
0#
#305
b111 "
b11111 $
b1 !
1#
#310
b10 !
0#
#315
b100000 $
b0 "
b11 !
1#
#320
b0 !
0#
#325
b1 "
b100001 $
b1 !
1#
#330
b10 !
0#
#335
b100010 $
b10 "
b11 !
1#
#340
b0 !
0#
#345
b11 "
b100011 $
b1 !
1#
#350
b10 !
0#
#355
b100100 $
b100 "
b11 !
1#
#360
b0 !
0#
#365
b101 "
b100101 $
b1 !
1#
#370
b10 !
0#
#375
b100110 $
b110 "
b11 !
1#
#380
b0 !
0#
#385
b111 "
b100111 $
b1 !
1#
#390
b10 !
0#
#395
b101000 $
b0 "
b11 !
1#
#400
b0 !
0#
#405
b1 "
b101001 $
b1 !
1#
#410
b10 !
0#
#415
b101010 $
b10 "
b11 !
1#
#420
b0 !
0#
#425
b11 "
b101011 $
b1 !
1#
#430
b10 !
0#
#435
b101100 $
b100 "
b11 !
1#
#440
b0 !
0#
#445
b101 "
b101101 $
b1 !
1#
#450
b10 !
0#
#455
b101110 $
b110 "
b11 !
1#
#460
b0 !
0#
#465
b111 "
b101111 $
b1 !
1#
#470
b10 !
0#
#475
b110000 $
b0 "
b11 !
1#
#480
b0 !
0#
#485
b1 "
b110001 $
b1 !
1#
#490
b10 !
0#
#495
b110010 $
b10 "
b11 !
1#
#500
b0 !
0#
#505
b11 "
b110011 $
b1 !
1#
#510
b10 !
0#
#515
b110100 $
b100 "
b11 !
1#
#520
b0 !
0#
#525
b101 "
b110101 $
b1 !
1#
#530
b10 !
0#
#535
b110110 $
b110 "
b11 !
1#
#540
b0 !
0#
#545
b111 "
b110111 $
b1 !
1#
#550
b10 !
0#
#555
b111000 $
b0 "
b11 !
1#
#560
b0 !
0#
#565
b1 "
b111001 $
b1 !
1#
#570
b10 !
0#
#575
b111010 $
b10 "
b11 !
1#
#580
b0 !
0#
#585
b11 "
b111011 $
b1 !
1#
#590
b10 !
0#
#595
b111100 $
b100 "
b11 !
1#
#600
b0 !
0#
#605
b101 "
b111101 $
b1 !
1#
#610
b10 !
0#
#615
b111110 $
b110 "
b11 !
1#
#620
b0 !
0#
#625
b111 "
b111111 $
b1 !
1#
#630
b10 !
0#
#635
b1000000 $
b0 "
b11 !
1#
#640
b0 !
0#
#645
b1 "
b1000001 $
b1 !
1#
#650
b10 !
0#
#655
b1000010 $
b10 "
b11 !
1#
#660
b0 !
0#
#665
b11 "
b1000011 $
b1 !
1#
#670
b10 !
0#
#675
b1000100 $
b100 "
b11 !
1#
#680
b0 !
0#
#685
b101 "
b1000101 $
b1 !
1#
#690
b10 !
0#
#695
b1000110 $
b110 "
b11 !
1#
#700
b0 !
0#
#705
b111 "
b1000111 $
b1 !
1#
#710
b10 !
0#
#715
b1001000 $
b0 "
b11 !
1#
#720
b0 !
0#
#725
b1 "
b1001001 $
b1 !
1#
#730
b10 !
0#
#735
b1001010 $
b10 "
b11 !
1#
#740
b0 !
0#
#745
b11 "
b1001011 $
b1 !
1#
#750
b10 !
0#
#755
b1001100 $
b100 "
b11 !
1#
#760
b0 !
0#
#765
b101 "
b1001101 $
b1 !
1#
#770
b10 !
0#
#775
b1001110 $
b110 "
b11 !
1#
#780
b0 !
0#
#785
b111 "
b1001111 $
b1 !
1#
#790
b10 !
0#
#795
b1010000 $
b0 "
b11 !
1#
#800
b0 !
0#
#805
b1 "
b1010001 $
b1 !
1#
#810
b10 !
0#
#815
b1010010 $
b10 "
b11 !
1#
#820
b0 !
0#
#825
b11 "
b1010011 $
b1 !
1#
#830
b10 !
0#
#835
b1010100 $
b100 "
b11 !
1#
#840
b0 !
0#
#845
b101 "
b1010101 $
b1 !
1#
#850
b10 !
0#
#855
b1010110 $
b110 "
b11 !
1#
#860
b0 !
0#
#865
b111 "
b1010111 $
b1 !
1#
#870
b10 !
0#
#875
b1011000 $
b0 "
b11 !
1#
#880
b0 !
0#
#885
b1 "
b1011001 $
b1 !
1#
#890
b10 !
0#
#895
b1011010 $
b10 "
b11 !
1#
#900
b0 !
0#
#905
b11 "
b1011011 $
b1 !
1#
#910
b10 !
0#
#915
b1011100 $
b100 "
b11 !
1#
#920
b0 !
0#
#925
b101 "
b1011101 $
b1 !
1#
#930
b10 !
0#
#935
b1011110 $
b110 "
b11 !
1#
#940
b0 !
0#
#945
b111 "
b1011111 $
b1 !
1#
#950
b10 !
0#
#955
b1100000 $
b0 "
b11 !
1#
#960
b0 !
0#
#965
b1 "
b1100001 $
b1 !
1#
#970
b10 !
0#
#975
b1100010 $
b10 "
b11 !
1#
#980
b0 !
0#
#985
b11 "
b1100011 $
b1 !
1#
#990
b10 !
0#
#995
b1100100 $
b100 "
b11 !
1#
#1000
b0 !
0#
#1005
b101 "
b1100101 $
b1 !
1#
#1010
b10 !
0#
